docs/source/conf.py
docs/source/rapyuta/__init__.py
riocli/__init__.py
riocli/__main__.py
riocli/bootstrap.py
riocli/apply/__init__.py
riocli/apply/explain.py
riocli/apply/filters.py
riocli/apply/parse.py
riocli/apply/template.py
riocli/apply/util.py
riocli/apply/manifests/deployment-nonros-cloud.yaml
riocli/apply/manifests/deployment-nonros-device.yaml
riocli/apply/manifests/deployment-ros-cloud.yaml
riocli/apply/manifests/deployment-ros-device-no-rosbag.yaml
riocli/apply/manifests/deployment-ros-device-rosbag.yaml
riocli/apply/manifests/deployment.yaml
riocli/apply/manifests/device-docker.yaml
riocli/apply/manifests/device-hybrid.yaml
riocli/apply/manifests/device-preinstalled.yaml
riocli/apply/manifests/device.yaml
riocli/apply/manifests/disk.yaml
riocli/apply/manifests/managedservice.yaml
riocli/apply/manifests/network-native-cloud.yaml
riocli/apply/manifests/network-native-device.yaml
riocli/apply/manifests/network-routed-cloud.yaml
riocli/apply/manifests/network-routed-device.yaml
riocli/apply/manifests/network.yaml
riocli/apply/manifests/package-nonros-cloud.yaml
riocli/apply/manifests/package-nonros-device.yaml
riocli/apply/manifests/package-ros-cloud.yaml
riocli/apply/manifests/package-ros-device-no-rosbag.yaml
riocli/apply/manifests/package-ros-device-rosbag.yaml
riocli/apply/manifests/package.yaml
riocli/apply/manifests/project.yaml
riocli/apply/manifests/secret-docker.yaml
riocli/apply/manifests/secret.yaml
riocli/apply/manifests/staticroute.yaml
riocli/apply/manifests/usergroup.yaml
riocli/auth/__init__.py
riocli/auth/login.py
riocli/auth/logout.py
riocli/auth/refresh_token.py
riocli/auth/staging.py
riocli/auth/status.py
riocli/auth/token.py
riocli/auth/util.py
riocli/chart/__init__.py
riocli/chart/apply.py
riocli/chart/chart.py
riocli/chart/delete.py
riocli/chart/info.py
riocli/chart/list.py
riocli/chart/search.py
riocli/chart/util.py
riocli/completion/__init__.py
riocli/config/__init__.py
riocli/config/config.py
riocli/config/context.py
rapyuta_io_cli_test-0.0.2.dist-info/LICENSE
rapyuta_io_cli_test-0.0.2.dist-info/METADATA
rapyuta_io_cli_test-0.0.2.dist-info/WHEEL
rapyuta_io_cli_test-0.0.2.dist-info/entry_points.txt
rapyuta_io_cli_test-0.0.2.dist-info/top_level.txt
rapyuta_io_cli_test-0.0.2.dist-info/RECORD
